jpl/pipedreams/VERSION.txt
jpl/pipedreams/__init__.py
jpl/pipedreams/celeryapp.py
jpl/pipedreams/data_pipe.py
jpl/pipedreams/plugins_ops.py
jpl/pipedreams/utils/__init__.py
jpl/pipedreams/utils/misc_utils.py
jpl_pipedreams-1.1.0.dist-info/METADATA
jpl_pipedreams-1.1.0.dist-info/WHEEL
jpl_pipedreams-1.1.0.dist-info/licenses/LICENSE.md
jpl_pipedreams-1.1.0.dist-info/licenses/NOTICE.md
jpl_pipedreams-1.1.0.dist-info/RECORD
