Metadata-Version: 2.4
Name: jpl.pipedreams
Version: 1.1.0
Summary: Pipe Dreams: API for publication of scientific data
Project-URL: Homepage, https://github.com/EDRN/jpl.pipedreams
Project-URL: Issues, https://github.com/EDRN/jpl.pipedreams/issues
Author-email: Asitang Mishra <asitang@gmail.com>, Sean Kelly <kelly@seankelly.biz>
License: Apache License
License-File: LICENSE.md
License-File: NOTICE.md
Keywords: analysis,archive,catalog,data,pipes,publication,science
Classifier: Development Status :: 3 - Alpha
Classifier: Environment :: Console
Classifier: Intended Audience :: Developers
Classifier: Intended Audience :: Science/Research
Classifier: License :: OSI Approved :: Apache Software License
Classifier: Operating System :: OS Independent
Classifier: Programming Language :: Python :: 3 :: Only
Classifier: Topic :: Database
Classifier: Topic :: Scientific/Engineering :: Bio-Informatics
Requires-Python: >=3.9
Requires-Dist: celery~=5.4.0
Requires-Dist: networkx~=2.8.8
Requires-Dist: redis~=5.2.1
Requires-Dist: tqdm~=4.67.1
